akernel/__init__.py
akernel/akernel.py
akernel/cache.py
akernel/code.py
akernel/connect.py
akernel/execution.py
akernel/kernel.py
akernel/kernelspec.py
akernel/message.py
akernel/traceback.py
akernel/IPython/__init__.py
akernel/IPython/core/__init__.py
akernel/IPython/core/getipython.py
akernel/IPython/core/interactiveshell.py
akernel/comm/__init__.py
akernel/comm/comm.py
akernel/comm/manager.py
akernel/display/__init__.py
akernel/display/display.py
akernel-0.3.4.data/data/share/jupyter/kernels/akernel/kernel.json
akernel-0.3.4.dist-info/METADATA
akernel-0.3.4.dist-info/WHEEL
akernel-0.3.4.dist-info/entry_points.txt
akernel-0.3.4.dist-info/licenses/LICENSE
akernel-0.3.4.dist-info/RECORD
