Metadata-Version: 2.4
Name: akernel
Version: 0.3.4
Summary: An asynchronous Python Jupyter kernel
Project-URL: Homepage, https://github.com/davidbrochart/akernel
Author-email: David Brochart <david.brochart@gmail.com>
License: MIT
License-File: LICENSE
Keywords: jupyter
Classifier: Development Status :: 4 - Beta
Classifier: Programming Language :: Python
Classifier: Programming Language :: Python :: 3.9
Classifier: Programming Language :: Python :: 3.10
Classifier: Programming Language :: Python :: 3.11
Classifier: Programming Language :: Python :: 3.12
Classifier: Programming Language :: Python :: 3.13
Classifier: Programming Language :: Python :: Implementation :: CPython
Classifier: Programming Language :: Python :: Implementation :: PyPy
Requires-Python: >=3.9
Requires-Dist: colorama
Requires-Dist: comm<1,>=0.1.3
Requires-Dist: gast<0.7.0,>=0.6.0
Requires-Dist: python-dateutil
Provides-Extra: cache
Requires-Dist: zict; extra == 'cache'
Provides-Extra: react
Requires-Dist: ipyx>=0.1.7; extra == 'react'
Provides-Extra: subprocess
Requires-Dist: typer>=0.4.0; extra == 'subprocess'
Requires-Dist: zmq-anyio<0.4.0,>=0.3.9; extra == 'subprocess'
